cog/__init__.py
cog/addition/__init__.py
cog/addition/addition.py
cog_ml_flow-0.2.dist-info/METADATA
cog_ml_flow-0.2.dist-info/WHEEL
cog_ml_flow-0.2.dist-info/top_level.txt
cog_ml_flow-0.2.dist-info/RECORD
