Metadata-Version: 2.1
Name: cog-ml-flow
Version: 0.2
Summary: cog mlflow
Home-page: 
Author: Veena Rao
Author-email: veena.rao@hiro-microdatacenters.nl
License: MIT
